MANIFEST.in
requirements.txt
setup.py
djangorestframework_digestauth.egg-info/PKG-INFO
djangorestframework_digestauth.egg-info/SOURCES.txt
djangorestframework_digestauth.egg-info/dependency_links.txt
djangorestframework_digestauth.egg-info/requires.txt
djangorestframework_digestauth.egg-info/top_level.txt
rest_framework_digestauth/__init__.py
rest_framework_digestauth/authentication.py
rest_framework_digestauth/models.py
rest_framework_digestauth/tests.py
rest_framework_digestauth/utils.py