Metadata-Version: 1.1
Name: djangorestframework-digestauth
Version: 1.1.0
Summary: Digest HTTP auth support for Django REST framework
Home-page: http://github.com/juanriaza/django-rest-framework-digestauth
Author: Juan Riaza
Author-email: juanriaza@gmail.com
License: BSD
Platform: UNKNOWN
Classifier: Development Status :: 4 - Beta
Classifier: Environment :: Web Environment
Classifier: Framework :: Django
Classifier: Intended Audience :: Developers
Classifier: License :: OSI Approved :: BSD License
Classifier: Operating System :: OS Independent
Classifier: Programming Language :: Python
Classifier: Topic :: Internet :: WWW/HTTP
